cellmaps_generate_hierarchy/__init__.py
cellmaps_generate_hierarchy/cellmaps_generate_hierarchycmd.py
cellmaps_generate_hierarchy/exceptions.py
cellmaps_generate_hierarchy/hcx.py
cellmaps_generate_hierarchy/hierarchy.py
cellmaps_generate_hierarchy/hierarchy_style.cx2
cellmaps_generate_hierarchy/interactome_style.cx2
cellmaps_generate_hierarchy/interactome_style_with_bait.cx2
cellmaps_generate_hierarchy/layout.py
cellmaps_generate_hierarchy/maturehierarchy.py
cellmaps_generate_hierarchy/ndexupload.py
cellmaps_generate_hierarchy/ppi.py
cellmaps_generate_hierarchy/readme_outputs.txt
cellmaps_generate_hierarchy/runner.py
cellmaps_generate_hierarchy-0.2.5.data/scripts/cellmaps_generate_hierarchycmd.py
cellmaps_generate_hierarchy-0.2.5.dist-info/AUTHORS.rst
cellmaps_generate_hierarchy-0.2.5.dist-info/LICENSE
cellmaps_generate_hierarchy-0.2.5.dist-info/METADATA
cellmaps_generate_hierarchy-0.2.5.dist-info/WHEEL
cellmaps_generate_hierarchy-0.2.5.dist-info/top_level.txt
cellmaps_generate_hierarchy-0.2.5.dist-info/RECORD
