Metadata-Version: 2.1
Name: cellmaps_generate_hierarchy
Version: 0.2.5
Summary: A tool to generate hierarchies from protein to protein interaction networks
Home-page: https://github.com/idekerlab/cellmaps_generate_hierarchy
Author: Cell Maps team
Author-email: tools@cm4ai.org
License: MIT license
Keywords: cellmaps_generate_hierarchy
Classifier: Development Status :: 2 - Pre-Alpha
Classifier: Intended Audience :: Developers
Classifier: License :: OSI Approved :: MIT License
Classifier: Natural Language :: English
Classifier: Programming Language :: Python :: 3.8
Classifier: Programming Language :: Python :: 3.9
Classifier: Programming Language :: Python :: 3.10
Classifier: Programming Language :: Python :: 3.11
License-File: LICENSE
License-File: AUTHORS.rst
Requires-Dist: cellmaps-utils <1.0.0,>=0.4.0
Requires-Dist: requests <3.0.0,>=2.31.0
Requires-Dist: tqdm <5.0.0,>=4.66.6
Requires-Dist: pandas <3.0.0,>=2.0.0
Requires-Dist: numpy <2.0.0,>=1.24.4
Requires-Dist: ndex2 <4.0.0,>=3.5.1
Requires-Dist: cdapsutil <1.0.0,>=0.2.2
Requires-Dist: leidenalg ==0.9.1
Requires-Dist: hidef <2.0.0,>=1.1.5
